psi/__init__.py
psi/cli.py
psi/wsgi.py
psi/app/__init__.py
psi/app/config.py
psi/app/const.py
psi/app/service.py
psi/app/socketio.py
psi/app/advice/__init__.py
psi/app/advice/inventory_advice.py
psi/app/api/__init__.py
psi/app/api/sales_order.py
psi/app/models/__init__.py
psi/app/models/aspects.py
psi/app/models/customer.py
psi/app/models/data_security_mixin.py
psi/app/models/enum_values.py
psi/app/models/expense.py
psi/app/models/image.py
psi/app/models/incoming.py
psi/app/models/inventory_in_out_link.py
psi/app/models/inventory_transaction.py
psi/app/models/organization.py
psi/app/models/product.py
psi/app/models/product_category.py
psi/app/models/product_inventory.py
psi/app/models/product_sales.py
psi/app/models/purchase_order.py
psi/app/models/receiving.py
psi/app/models/related_values.py
psi/app/models/report_base_model.py
psi/app/models/role.py
psi/app/models/sales_order.py
psi/app/models/shipping.py
psi/app/models/supplier.py
psi/app/models/supplier_sales.py
psi/app/models/user.py
psi/app/reports/__init__.py
psi/app/reports/handlers_config.py
psi/app/reports/report.py
psi/app/reports/sales_order_reports.py
psi/app/reports/sqls.py
psi/app/services/__init__.py
psi/app/services/purchase_order.py
psi/app/services/sales_order.py
psi/app/thirdparty/__init__.py
psi/app/thirdparty/cloudinary_image_store.py
psi/app/thirdparty/local_image_store.py
psi/app/translations/zh_Hans_CN/LC_MESSAGES/messages.mo
psi/app/translations/zh_Hans_CN/LC_MESSAGES/messages.po
psi/app/utils/__init__.py
psi/app/utils/date_util.py
psi/app/utils/db_util.py
psi/app/utils/decorations.py
psi/app/utils/file_util.py
psi/app/utils/form_util.py
psi/app/utils/format_util.py
psi/app/utils/security_util.py
psi/app/utils/ui_util.py
psi/app/views/__init__.py
psi/app/views/base.py
psi/app/views/base_purchase_order.py
psi/app/views/customer.py
psi/app/views/direct_purchase_order.py
psi/app/views/enum_values.py
psi/app/views/expense.py
psi/app/views/formatter.py
psi/app/views/franchise_purchase_order.py
betterlifepsi-0.6.8.dist-info/LICENSE.txt
betterlifepsi-0.6.8.dist-info/METADATA
betterlifepsi-0.6.8.dist-info/WHEEL
betterlifepsi-0.6.8.dist-info/top_level.txt
betterlifepsi-0.6.8.dist-info/RECORD
