Metadata-Version: 2.1
Name: betterlifepsi
Version: 0.6.8
Summary: Betterlife Intelligent PSI(Purchase, Sales and Inventory) system
Home-page: https://github.com/betterlife/psi
Author: Lawrence Liu
Author-email: lawrence@betterlife.io
License: MIT
Keywords: Betterlife,Intelligent,Purchase Order,Sales Order,Inventory Management,Retail
Platform: UNKNOWN
Classifier: Development Status :: 2 - Pre-Alpha
Classifier: License :: OSI Approved :: MIT License
Classifier: Operating System :: OS Independent
Classifier: Programming Language :: Python :: 3.4
Classifier: Programming Language :: Python :: 3.5
Classifier: Programming Language :: Python :: 3.6
Classifier: Programming Language :: Python :: 3.7
Classifier: Topic :: Office/Business :: Financial :: Point-Of-Sale
Classifier: Topic :: Office/Business :: Financial
Classifier: Topic :: Office/Business :: Financial :: Accounting
Classifier: Natural Language :: Chinese (Simplified)
Classifier: Natural Language :: English
Classifier: Framework :: Flask
Requires-Dist: Flask (==1.0.2)
Requires-Dist: Jinja2 (==2.10)
Requires-Dist: Flask-Admin (==1.5.2)
Requires-Dist: sqlalchemy (==1.2.13)
Requires-Dist: Flask-SQLAlchemy (==2.3.2)
Requires-Dist: Flask-SSLify (==0.1.5)
Requires-Dist: MarkupSafe (==1.0)
Requires-Dist: Werkzeug (==0.14.1)
Requires-Dist: gunicorn (==19.9.0)
Requires-Dist: Flask-BabelEx (==0.9.3)
Requires-Dist: raven (==6.9.0)
Requires-Dist: Flask-Migrate (==2.3.0)
Requires-Dist: Flask-Security (==3.0.0)
Requires-Dist: Flask-DebugToolbar (==0.10.1)
Requires-Dist: cloudinary (==1.14.0)
Requires-Dist: Flask-RESTful (==0.3.6)
Requires-Dist: flask-socketio (==3.0.1)
Requires-Dist: eventlet (==0.24.1)
Requires-Dist: pypinyin (==0.33.2)
Requires-Dist: python-dotenv (==0.9.1)
